README.txt
bootstrap.py
buildout.cfg
setup.py
docs/HISTORY.txt
src/megrok/__init__.py
src/megrok.z3cform.tabular.egg-info/PKG-INFO
src/megrok.z3cform.tabular.egg-info/SOURCES.txt
src/megrok.z3cform.tabular.egg-info/dependency_links.txt
src/megrok.z3cform.tabular.egg-info/entry_points.txt
src/megrok.z3cform.tabular.egg-info/namespace_packages.txt
src/megrok.z3cform.tabular.egg-info/not-zip-safe
src/megrok.z3cform.tabular.egg-info/requires.txt
src/megrok.z3cform.tabular.egg-info/top_level.txt
src/megrok/z3cform/__init__.py
src/megrok/z3cform/tabular/README.txt
src/megrok/z3cform/tabular/__init__.py
src/megrok/z3cform/tabular/components.py
src/megrok/z3cform/tabular/configure.zcml
src/megrok/z3cform/tabular/ftesting.zcml
src/megrok/z3cform/tabular/tests/__init__.py
src/megrok/z3cform/tabular/tests/test_deleteTable.py
src/megrok/z3cform/tabular/tests/test_formtableinlayout.py
src/megrok/z3cform/tabular/tests/test_readme.py
src/megrok/z3cform/tabular/tests/test_tabular.py
src/megrok/z3cform/tabular/tests/test_formtableinlayout_templates/formtablepagewithtemplate.pt
src/megrok/z3cform/tabular/tests/test_tabular_templates/contentstablewithtemplate.pt