Metadata-Version: 1.0
Name: megrok.z3cform.tabular
Version: 0.2
Summary: Grok addon for createing tabular forms
Home-page: UNKNOWN
Author: Christian Klinger
Author-email: cklinger@novareto.de
License: GPL
Keywords: grok z3c.form megrok.z3cform.wizard
Platform: UNKNOWN
Classifier: Programming Language :: Python
Classifier: Topic :: Software Development :: Libraries :: Python Modules
